Workbook
Name aporte: Simulador!$D$16
Name patrimonio: Simulador!$D$19
Name qtd_anos: Simulador!$D$17
Name rendimento_carteira: Simulador!$D$12
Name salario: Simulador!$D$11
Name sugestao_investimento: Simulador!$D$13
Name taxa_mensal: Simulador!$D$18

Sheet Simulador
B10: CONFIGURAÇÕES
B11: Salário | D11: 2000
B12: Rendimento carteira | D12: 0.006
B13: Sugestão de investimento | D13: =D11*30% -> 600
B15: INVESTIMENTO MENSAL
B16: Quanto investir por mês? | D16: 200
B17: Por quantos anos? | D17: 5
B18: Taxa de Rendimentos mensal? | D18: 0.0108
B19: Patrimônio acumulado? | D19: =FV(taxa_mensal,qtd_anos*12,aporte*-1) -> 16760.804
B20: Dividendos mensais? | D20: =patrimonio*rendimento_carteira -> 100.56482
B22: Cenários | D22: Dividendo
A23: 2 | B23: Quanto em 2 anos? | C23: =FV($D$18,$A23*12,$D$16*-1) -> 5446.1727 | D23: =C23*rendimento_carteira -> 32.677036
A24: 5 | B24: Quanto em 5 anos? | C24: =FV($D$18,$A24*12,$D$16*-1) -> 16760.804 | D24: =C24*rendimento_carteira -> 100.56482
A25: 10 | B25: Quanto em 10 anos? | C25: =FV($D$18,$A25*12,$D$16*-1) -> 48691.533 | D25: =C25*rendimento_carteira -> 292.1492
A26: 20 | B26: Quanto em 20 anos? | C26: =FV($D$18,$A26*12,$D$16*-1) -> 225409.8 | D26: =C26*rendimento_carteira -> 1352.4588
A27: 30 | B27: Quanto em 30 anos? | C27: =FV($D$18,$A27*12,$D$16*-1) -> 866780.96 | D27: =C27*rendimento_carteira -> 5200.6858
B32: PERFIL | C32: Agressivo
B33: VALOR A SER INVESTIDO POR MÊS | C33: =aporte -> 200
B35: TIPO DE FII | C35: Percentual Sugerido | D35: Valores
B36: PAPEL | C36: =VLOOKUP($C$32&"-"&B36,Apoio_Perfis!$A:$D,4,) -> 0.5 | D36: =C36*$C$33 -> 100
B37: TIJOLO | C37: =VLOOKUP($C$32&"-"&B37,Apoio_Perfis!$A:$D,4,) -> 0.1 | D37: =C37*$C$33 -> 20
B38: HÍBRIDOS | C38: =VLOOKUP($C$32&"-"&B38,Apoio_Perfis!$A:$D,4,) -> 0.05 | D38: =C38*$C$33 -> 10
B39: FOFs | C39: =VLOOKUP($C$32&"-"&B39,Apoio_Perfis!$A:$D,4,) -> 0.05 | D39: =C39*$C$33 -> 10
B40: DESENVOLVIMENTOS | C40: =VLOOKUP($C$32&"-"&B40,Apoio_Perfis!$A:$D,4,) -> 0.2 | D40: =C40*$C$33 -> 40
B41: HOTELARIAS | C41: =VLOOKUP($C$32&"-"&B41,Apoio_Perfis!$A:$D,4,) -> 0.1 | D41: =C41*$C$33 -> 20
D42: =SUM(D36:D41) -> 200

Sheet Apoio_Perfis
A2: CHAVE | B2: PERFIS | C2: TIPO DE FII | D2: %
A3: =B3&"-"&C3 -> CONSERVADOR-PAPEL | B3: CONSERVADOR | C3: PAPEL | D3: 0.3 | H3: %
A4: =B4&"-"&C4 -> CONSERVADOR-TIJOLO | B4: CONSERVADOR | C4: TIJOLO | D4: 0.5 | G4: MODERADO-TIJOLO | H4: =VLOOKUP(G4,$A:$D,4,) -> 0.35
A5: =B5&"-"&C5 -> CONSERVADOR-HÍBRIDOS | B5: CONSERVADOR | C5: HÍBRIDOS | D5: 0.1
A6: =B6&"-"&C6 -> CONSERVADOR-FOFs | B6: CONSERVADOR | C6: FOFs | D6: 0.1
A7: =B7&"-"&C7 -> CONSERVADOR-DESENVOLVIMENTOS | B7: CONSERVADOR | C7: DESENVOLVIMENTOS | D7: 0
A8: =B8&"-"&C8 -> CONSERVADOR-HOTELARIAS | B8: CONSERVADOR | C8: HOTELARIAS | D8: 0
A9: =B9&"-"&C9 -> MODERADO-PAPEL | B9: MODERADO | C9: PAPEL | D9: 0.32
A10: =B10&"-"&C10 -> MODERADO-TIJOLO | B10: MODERADO | C10: TIJOLO | D10: 0.35
A11: =B11&"-"&C11 -> MODERADO-HÍBRIDOS | B11: MODERADO | C11: HÍBRIDOS | D11: 0.08
A12: =B12&"-"&C12 -> MODERADO-FOFs | B12: MODERADO | C12: FOFs | D12: 0.05
A13: =B13&"-"&C13 -> MODERADO-DESENVOLVIMENTOS | B13: MODERADO | C13: DESENVOLVIMENTOS | D13: 0.1
A14: =B14&"-"&C14 -> MODERADO-HOTELARIAS | B14: MODERADO | C14: HOTELARIAS | D14: 0.1
A15: =B15&"-"&C15 -> AGRESSIVO-PAPEL | B15: AGRESSIVO | C15: PAPEL | D15: 0.5
A16: =B16&"-"&C16 -> AGRESSIVO-TIJOLO | B16: AGRESSIVO | C16: TIJOLO | D16: 0.1
... A20: =B20&"-"&C20 -> AGRESSIVO-HOTELARIAS | B20: AGRESSIVO | C20: HOTELARIAS | D20: 0.1
